EmailSender/__init__.py
EmailSender/config.py
EmailSender/sender.py
EmailSenderVaryTest/__init__.py
EmailSenderVaryTest/config.py
EmailSenderVaryTest/sender.py
EmailSender_GhostPoltergeist/__init__.py
EmailSender_GhostPoltergeist/config.py
EmailSender_GhostPoltergeist/sender.py
EmailSender_GhostPoltergeist-2.1.0.dist-info/LICENSE.txt
EmailSender_GhostPoltergeist-2.1.0.dist-info/METADATA
EmailSender_GhostPoltergeist-2.1.0.dist-info/WHEEL
EmailSender_GhostPoltergeist-2.1.0.dist-info/top_level.txt
EmailSender_GhostPoltergeist-2.1.0.dist-info/RECORD
